tkvideo/__init__.py
tkvideo/tkvideo.py
tkVideo-0.1.dist-info/LICENSE
tkVideo-0.1.dist-info/METADATA
tkVideo-0.1.dist-info/WHEEL
tkVideo-0.1.dist-info/top_level.txt
tkVideo-0.1.dist-info/RECORD
