Metadata-Version: 2.1
Name: tkVideo
Version: 0.1
Summary: Python module for playing videos (without sound) inside tkinter Label widget using Pillow and imageio
Home-page: https://github.com/huskeee/tkvideo
Author: Xenofon Konitsas (huskee)
Author-email: konitsasx@gmail.com
License: MIT
Keywords: tkvideo tkinter video display label pillow imageio huskee
Platform: UNKNOWN
Classifier: Development Status :: 4 - Beta
Classifier: License :: OSI Approved :: MIT License
Classifier: Programming Language :: Python :: 3.9
Classifier: Topic :: Multimedia :: Video :: Display
